{"title":"SMTOWN ─ Musicians News","url":"https://www.smtown.com/artist/news/1","favicon":"https://www.smtown.com/artist/news/favicon.ico","elements":[{"title":"최강창민, 새 앨범 ‘Devil’로 들려줄 다채로운 보컬 매력!","contents":"<span class=\"name\"></span>\n                                        <span class=\"title\">최강창민, 새 앨범 ‘Devil’로 들려줄 다채로운 보컬 매력!</span>","link":"https://www.smtown.com/artist/newsDetail/5841","retrieved":1641872828540,"image":"https://smcdn.smtown.com/file/newsfeed/202201/star_61dcfdb564d3b.jpg"},{"title":"‘컴백 D-3’ 최강창민, 새 앨범 수록곡 ‘Maniac’ 비디오 10일 오후 6시 공개!","contents":"<span class=\"name\"></span>\n                                        <span class=\"title\">‘컴백 D-3’ 최강창민, 새 앨범 수록곡 ‘Maniac’ 비디오 10일 오후 6시 공개!</span>","link":"https://www.smtown.com/artist/newsDetail/5839","retrieved":1641790589996,"image":"https://smcdn.smtown.com/file/newsfeed/202201/star_61dbad3633afa.jpg"}]}