{"title":"SMTOWN ─ Musicians News","url":"https://www.smtown.com/artist/news/1","favicon":"https://www.smtown.com/artist/news/favicon.ico","elements":[{"title":"DJ 스트리밍 쇼 ‘SHOWME’ 6번째 주자, 안톤 출격!","contents":"<span class=\"name\"></span>\n                                        <span class=\"title\">DJ 스트리밍 쇼 ‘SHOWME’ 6번째 주자, 안톤 출격!</span>","link":"https://www.smtown.com/artist/newsDetail/5953","retrieved":1644558002107,"image":"https://smcdn.smtown.com/file/newsfeed/202202/star_6205ed8da951f.jpg"},{"title":"NCT, ‘THE NCT SHOW’ 론칭!","contents":"<span class=\"name\"></span>\n                                        <span class=\"title\">NCT, ‘THE NCT SHOW’ 론칭!</span>","link":"https://www.smtown.com/artist/newsDetail/5952","retrieved":1644554951878,"image":"https://smcdn.smtown.com/file/newsfeed/202202/star_6205dbc735c13.jpg"}]}