{"title":"SMTOWN ─ Actors News","url":"https://www.smtown.com/artist/news/2","favicon":"https://www.smtown.com/artist/news/favicon.ico","elements":[{"title":"윤보라, JTBC ‘한 사람만’ 출연… 데뷔 후 첫 수녀 역 도전","contents":"<span class=\"name\"></span>\n                                        <span class=\"title\">윤보라, JTBC ‘한 사람만’ 출연… 데뷔 후 첫 수녀 역 도전</span>","link":"https://www.smtown.com/artist/newsDetail/5713","retrieved":1639032739871,"image":"https://smcdn.smtown.com/file/newsfeed/202112/star_61b197457add8.jpg"},{"title":"JTBC ‘공작도시’ 이학주, 순수+열정 가득 보도국 기자 ‘한동민’役 첫등장","contents":"<span class=\"name\"></span>\n                                        <span class=\"title\">JTBC ‘공작도시’ 이학주, 순수+열정 가득 보도국 기자 ‘한동민’役 첫등장</span>","link":"https://www.smtown.com/artist/newsDetail/5712","retrieved":1639028546489,"image":"https://smcdn.smtown.com/file/newsfeed/202112/star_61b196ede20bd.jpg"}]}