{"title":"SMTOWN ─ Musicians News","url":"https://www.smtown.com/artist/news/1","favicon":"https://www.smtown.com/artist/news/favicon.ico","elements":[{"title":"NCT 127-NCT DREAM, 나란히 음반 판매량 300만장 돌파 ‘겹경사’","contents":"<span class=\"name\"></span>\n                                        <span class=\"title\">NCT 127-NCT DREAM, 나란히 음반 판매량 300만장 돌파 ‘겹경사’</span>","link":"https://www.smtown.com/artist/newsDetail/5603","retrieved":1636343153138,"image":"https://smcdn.smtown.com/file/newsfeed/202111/star_618897302db02.jpg"},{"title":"SM ‘리마스터링 프로젝트’ 뮤직비디오 매주 목요일 순차 공개!","contents":"<span class=\"name\"></span>\n                                        <span class=\"title\">SM ‘리마스터링 프로젝트’ 뮤직비디오 매주 목요일 순차 공개!</span>","link":"https://www.smtown.com/artist/newsDetail/5602","retrieved":1636343153139,"image":"https://smcdn.smtown.com/file/newsfeed/202111/star_618896c0a454a.jpg"}]}